tabmark/__init__.py
tabmark/utils.py
tabmark/datasets/__init__.py
tabmark/datasets/datasets.py
tabmark/datasets/pytorch_datasets.py
tabmark-0.0.3.dist-info/METADATA
tabmark-0.0.3.dist-info/WHEEL
tabmark-0.0.3.dist-info/licenses/LICENSE
tabmark-0.0.3.dist-info/RECORD
