Metadata-Version: 2.1
Name: tabmark
Version: 0.0.3
Summary: A tabular dataset benchmark compatible with PyTorch
Project-URL: Homepage, https://github.com/MatthiasJakobs/tabmark
Author-email: Matthias Jakobs <matthias.jakobs@tu-dortmund.de>
License-File: LICENSE
Classifier: License :: OSI Approved :: MIT License
Classifier: Operating System :: OS Independent
Classifier: Programming Language :: Python :: 3
Requires-Python: >=3.7
Requires-Dist: numpy
Requires-Dist: scikit-learn
